examples/__init__.py
examples/demohub.py
wigglecam/__init__.py
wigglecam/__main__.py
wigglecam/app.py
wigglecam/backends/__init__.py
wigglecam/backends/cameras/__init__.py
wigglecam/backends/cameras/base.py
wigglecam/backends/cameras/output/base.py
wigglecam/backends/cameras/output/pynng.py
wigglecam/backends/cameras/picam.py
wigglecam/backends/cameras/virtual.py
wigglecam/backends/triggers/__init__.py
wigglecam/backends/triggers/input/base.py
wigglecam/backends/triggers/input/pynng.py
wigglecam/config/__init__.py
wigglecam/config/app.py
wigglecam/config/base.py
wigglecam/config/camera_picamera2.py
wigglecam/config/camera_virtual.py
wigglecam/config/trigger_pynng.py
wigglecam/dto.py
wigglecam-0.4.1.dist-info/WHEEL
wigglecam-0.4.1.dist-info/entry_points.txt
wigglecam-0.4.1.dist-info/METADATA
wigglecam-0.4.1.dist-info/RECORD
