Metadata-Version: 2.3
Name: wigglecam
Version: 0.4.1
Summary: Wigglecam package help you building an awesome camera.
Keywords: wigglecam,wigglecamera,stereoscopic,picamera2,picamera,camera,python,synchronized camera
Author: Michael G
Author-email: Michael G <me@mgineer85.de>
License: MIT
Classifier: License :: OSI Approved :: MIT License
Classifier: Operating System :: OS Independent
Classifier: Programming Language :: Python :: 3
Classifier: Programming Language :: Python :: 3.11
Classifier: Programming Language :: Python :: 3.12
Classifier: Programming Language :: Python :: 3.13
Classifier: Programming Language :: Python :: 3.14
Classifier: Topic :: Multimedia :: Graphics
Classifier: Topic :: Software Development :: Libraries :: Python Modules
Classifier: Topic :: Multimedia :: Graphics :: Capture :: Digital Camera
Requires-Dist: opencv-python>=4.10.0.84 ; extra == 'demohub'
Requires-Dist: pydantic ; extra == 'node'
Requires-Dist: pydantic-settings ; extra == 'node'
Requires-Dist: opencv-python-headless>=4.10.0.84 ; extra == 'node'
Requires-Dist: pynng ; extra == 'node'
Requires-Dist: pillow>=11.0.0 ; extra == 'node'
Maintainer: Michael G
Maintainer-email: Michael G <me@mgineer85.de>
Requires-Python: >=3.11
Project-URL: documentation, https://photobooth-app.org/wigglegramcamera/
Project-URL: homepage, https://photobooth-app.org/wigglegramcamera/
Project-URL: repository, https://github.com/photobooth-app/wigglecam
Provides-Extra: demohub
Provides-Extra: node
